{
  "id": "e7d5c3a0-9d15-4d6c-8c46-79b1a4c9f111",
  "name": "Salon Local",
  "values": [
    { "key": "baseUrl", "value": "http://127.0.0.1:8000/api/v1", "enabled": true },
    { "key": "access_token", "value": "YOUR_ACCESS_TOKEN", "enabled": true },
    { "key": "refresh_token", "value": "YOUR_REFRESH_TOKEN", "enabled": true },
    { "key": "user_id", "value": "YOUR_USER_ID", "enabled": true },
    { "key": "branch_id", "value": "YOUR_BRANCH_ID", "enabled": true },
    { "key": "manager_id", "value": "YOUR_MANAGER_ID", "enabled": true },
    { "key": "employee_id", "value": "YOUR_EMPLOYEE_ID", "enabled": true },
    { "key": "daily_entry_id", "value": "YOUR_DAILY_ENTRY_ID", "enabled": true },
    { "key": "day_closure_id", "value": "YOUR_DAY_CLOSURE_ID", "enabled": true },
    { "key": "ledger_party_type", "value": "employee", "enabled": true },
    { "key": "ledger_party_id", "value": "YOUR_LEDGER_PARTY_ID", "enabled": true },
    { "key": "advance_request_id", "value": "YOUR_ADVANCE_REQUEST_ID", "enabled": true },
    { "key": "document_id", "value": "YOUR_DOCUMENT_ID", "enabled": true },
    { "key": "document_owner_type", "value": "employee", "enabled": true },
    { "key": "document_owner_id", "value": "YOUR_DOCUMENT_OWNER_ID", "enabled": true },
    { "key": "notification_id", "value": "YOUR_NOTIFICATION_ID", "enabled": true }
  ],
  "_postman_variable_scope": "environment",
  "_postman_exported_at": "2025-01-01T00:00:00.000Z",
  "_postman_exported_using": "Postman/10.0.0"
}
